{
  "recentFiles": [
    {
      "basename": "2. 3D Data Acquisition (Passive)",
      "path": "20. Lecture Note/3D Point Cloud Data Processing/2. 3D Data Acquisition (Passive).md"
    },
    {
      "basename": "Epipolar Plane",
      "path": "20. Lecture Note/3D Point Cloud Data Processing/Epipolar Plane.md"
    },
    {
      "basename": "Epipolar Line",
      "path": "20. Lecture Note/3D Point Cloud Data Processing/Epipolar Line.md"
    },
    {
      "basename": "Epipole",
      "path": "20. Lecture Note/3D Point Cloud Data Processing/Epipole.md"
    },
    {
      "basename": "README",
      "path": "README.md"
    },
    {
      "basename": "Robotics and AI",
      "path": "Robotics and AI.md"
    }
  ],
  "omittedPaths": []
}