{
  "recentFiles": [
    {
      "basename": "2. 3D Data Acquisition (Passive)",
      "path": "20. Lecture Note/3D Point Cloud Data Processing/2. 3D Data Acquisition (Passive).md"
    },
    {
      "basename": "2. Vector Part1",
      "path": "20. Lecture Note/Linear Algebra/2. Vector Part1.md"
    },
    {
      "basename": "Python - Day2",
      "path": "20. Lecture Note/Python Basic/Python - Day2.md"
    },
    {
      "basename": "Python - Day3",
      "path": "20. Lecture Note/Python Basic/Python - Day3.md"
    },
    {
      "basename": "Python - Day7",
      "path": "20. Lecture Note/Python Basic/Python - Day7.md"
    },
    {
      "basename": "Robotics and AI",
      "path": "Robotics and AI.md"
    },
    {
      "basename": "Untitled - 2024-07-25",
      "path": "20. Lecture Note/3D Point Cloud Data Processing/Untitled - 2024-07-25.md"
    },
    {
      "basename": "새 프로젝트 노트(New Project Note)",
      "path": "90. Template/새 프로젝트 노트(New Project Note).md"
    },
    {
      "basename": "새 수강 과목 (New Subject)",
      "path": "90. Template/새 수강 과목 (New Subject).md"
    },
    {
      "basename": "새 데일리 노트(New Daily Note)",
      "path": "90. Template/새 데일리 노트(New Daily Note).md"
    },
    {
      "basename": "새 과제 (New Assignment)",
      "path": "90. Template/새 과제 (New Assignment).md"
    },
    {
      "basename": "새 강의 노트(New Lecture Note)",
      "path": "90. Template/새 강의 노트(New Lecture Note).md"
    },
    {
      "basename": "Team Cheetah Side Project",
      "path": "50.Projects/Team Cheetah Side Project.md"
    },
    {
      "basename": "Epipolar Plane",
      "path": "기초 개념/Epipolar Plane.md"
    },
    {
      "basename": "Epipolar Line",
      "path": "기초 개념/Epipolar Line.md"
    },
    {
      "basename": "Epipole",
      "path": "기초 개념/Epipole.md"
    },
    {
      "basename": "README",
      "path": "README.md"
    }
  ],
  "omittedPaths": []
}